{
    "Config" :
    {
        "Background" :
        {
            "Color" : "0 255 0",
            "Texture" : "backgrond.jpg",
            "PositionX" : 0,
            "PositionY" : 0,
            "FitScreen" : false,
            "OverrideSize" : false,
            "UseWallpaper" : false,
            "Width" : 0,
            "Height" : 0
        },

        "Boids" :
        {
            "Count" : 20000,
            "Width" : 22.0,
            "Height" : 11.0,
            "SpeedMax" : 240.0,
            "SpeedMin" : 80.0,
            "SteerMax" : 4.0,
            "ViewAngle" : 280.0
        },
        
        "Rules" :
        {
            "SepDistance" : 12.0,
            "AliDistance" : 20.0,
            "CohDistance" : 20.0,

            "SepWeight" : 4.00,
            "AliWeight" : 1.75,
            "CohWeight" : 1.50
        },

        "Interaction" :
        {
            "BoidAddAmount" : 5,
            "BoidAddMouseDiff" : 1.0,
            "BoidRemoveAmount" : 50,

            "SteerEnabled" : true,
            "SteerTowardsFactor" : 256.0,
            "SteerAwayFactor" : 256.0,

            "PredatorEnabled" : false,
            "PredatorDistance" : 250.0,
            "PredatorFactor" : 8.0,

            "TurnAtBorder" : false,
            "TurnMarginFactor" : 0.5,
            "TurnFactor" : 2000.0
        },

        "Color" : 
        {
            "ColorOptions" : [ 2, 3, 4, 5, 6, 7 ],

            "ColorPositionalWeight" : 1.0,
            "ColorCycleWeight" : 0.2,
            "ColorDensityWeight" : 0.5,
            "ColorVelocityWeight" : 0.6,
            "ColorRotationWeight" : -1.2,
            "ColorAudioWeight" : 0.6,
            "ColorFluidWeight" : 1.0,

            "TopLeft" : "255 20 255",
            "TopRight" : "150 0 255",
            "BotLeft" : "216 191 216",
            "BotRight" : "90 0 90",
            
            "CycleRandom" : true,
            "CycleSpeed" : 1.0,
            "CycleColors" : 
            [
                "90 0 90",
                "255 20 255", 
                "150 0 255", 
                "90 0 90"
            ],

            "Density" : 70,
            "DensityCycleEnabled" : true,
            "DensityCycleSpeed" : 0.75,
            "DensityColors" : 
            [
                "90 0 90",
                "90 0 90",
                "90 0 90",
                "90 0 90",
                "90 0 90",
                "255 20 255",
                "150 0 255",
                "90 0 90"
            ],

            "VelocityColors" :
            [
                "0 0 0",
                "0 0 0",
                "0 0 0",
                "0 0 0",
                "0 0 0",
                "0 0 0",
                "0 0 0",
                "0 0 0",
                "90 0 90",
                "90 0 90",
                "150 0 255",
                "150 0 255",
                "255 20 255"
            ],

            "RotationColors" :
            [
                "45 0 45",
                "45 0 45",
                "90 0 90",
                "90 0 90",
                "90 0 90",
                "75 0 75",
                "75 0 75"
            ],

            "AudioApps" : [ "Spotify.exe" ],
            "AudioStrength" : 6.0,
            "AudioLimit" : 1.2,
            "AudioSpeed" : 50.0,
            "AudioDensity" : 20,
            "AudioColors" : 
            [
                "0 0 0",
                "0 0 0",
                "0 0 0",
                "90 0 90",
                "150 0 255",
                "0 0 0",
                "0 0 0",
                "90 0 90",
                "150 0 255",
                "200 10 255",
                "0 0 0"
            ],

            "FluidScale" : 25,
            "FluidMouseStrength" : 0.8,
            "FluidColorVel" : 0.3,
            "FluidDiffusion" : 0.0,
            "FluidViscosity" : 0.000005,
            "FluidColors" :
            [
                "0 0 0",
                "0 0 0",
                "90 0 90",
                "90 0 90",
                "90 0 90",
                "150 0 255",
                "150 0 255",
                "150 0 255",
                "255 20 255"
            ],

            "ImpulseEnabled" : true,
            "ImpulseSize" : 50.0,
            "ImpulseSpeed" : 400.0,
            "ImpulseFadeDistance" : 300.0,
            "ImpulseForce" : 256.0,
            "ImpulseColors" :
            [
                "255 20 255",
                "255 20 255",
                "255 20 255",
                "150 0 255",
                "150 0 255", 
                "90 0 90"
            ]
        },

        "Misc" : 
        {
            "GridExtraCells" : 16,
            "CameraEnabled" : false,
            "CameraZoom" : 1.0,
            "VerticalSync" : false,
            "MaxFramerate" : 0,
            "PhysicsUpdateFreq" : 60,
            "PolicyThreshold" : 1500,

            "DebugEnabled" : true,
            "DebugUpdateFreq" : 0.5,
            "DebugToggleKey" : 85
        }
    }
}